api_orm/__init__.py
api_orm-0.0.0.dev1.dist-info/LICENSE
api_orm-0.0.0.dev1.dist-info/METADATA
api_orm-0.0.0.dev1.dist-info/WHEEL
api_orm-0.0.0.dev1.dist-info/top_level.txt
api_orm-0.0.0.dev1.dist-info/RECORD
