Metadata-Version: 2.1
Name: api-orm
Version: 0.0.0.dev1
Summary: Interact with API endpoints as Python objects and manage resources in an ORMy way
Home-page: https://github.com/pwitab/api-orm
Author: Henrik Palmlund Wahlgren @ Palmlund Wahlgren Innovative Technology AB
Author-email: henrik@pwit.se
License: BSD-3
Keywords: api,orm
Platform: UNKNOWN
Classifier: Development Status :: 3 - Alpha
Classifier: License :: OSI Approved :: BSD License
Classifier: Natural Language :: English
Classifier: Programming Language :: Python
Classifier: Programming Language :: Python :: 3
Classifier: Programming Language :: Python :: 3 :: Only
Classifier: Programming Language :: Python :: 3.6
Classifier: Topic :: Software Development :: Libraries
Requires-Python: >=3.6
Requires-Dist: marshmallow (>=3.0.0b1)
